<featureType>
  <id>FeatureTypeInfoImpl-1aca7038:136e4c494b4:-7ff3</id>
  <name>country_facts_1990</name>
  <nativeName>ged4gem_gadm_country_facts_90</nativeName>
  <namespace>
    <id>NamespaceInfoImpl-2e2377f3:136536dfbc1:-7ffe</id>
  </namespace>
  <title>country_facts_1990</title>
  <abstract>No abstract provided</abstract>
  <keywords>
    <string></string>
  </keywords>
  <metadataLinks>
    <metadataLink>
      <type>text/xml</type>
      <metadataType>TC211</metadataType>
      <content>http://178.79.187.26/geonetwork/srv/en/csw?outputschema=http%3A%2F%2Fwww.isotc211.org%2F2005%2Fgmd&amp;service=CSW&amp;request=GetRecordById&amp;version=2.0.2&amp;elementsetname=full&amp;id=a438bddd-4d76-4648-81bc-59120453c23a</content>
    </metadataLink>
  </metadataLinks>
  <nativeCRS>GEOGCS[&quot;WGS 84&quot;, 
  DATUM[&quot;World Geodetic System 1984&quot;, 
    SPHEROID[&quot;WGS 84&quot;, 6378137.0, 298.257223563, AUTHORITY[&quot;EPSG&quot;,&quot;7030&quot;]], 
    AUTHORITY[&quot;EPSG&quot;,&quot;6326&quot;]], 
  PRIMEM[&quot;Greenwich&quot;, 0.0, AUTHORITY[&quot;EPSG&quot;,&quot;8901&quot;]], 
  UNIT[&quot;degree&quot;, 0.017453292519943295], 
  AXIS[&quot;Geodetic longitude&quot;, EAST], 
  AXIS[&quot;Geodetic latitude&quot;, NORTH], 
  AUTHORITY[&quot;EPSG&quot;,&quot;4326&quot;]]</nativeCRS>
  <srs>EPSG:4326</srs>
  <nativeBoundingBox>
    <minx>-179.991</minx>
    <maxx>180.0</maxx>
    <miny>-55.984</miny>
    <maxy>83.627</maxy>
    <crs>EPSG:4326</crs>
  </nativeBoundingBox>
  <latLonBoundingBox>
    <minx>-179.991</minx>
    <maxx>180.0</maxx>
    <miny>-55.984</miny>
    <maxy>83.627</maxy>
    <crs>EPSG:4326</crs>
  </latLonBoundingBox>
  <projectionPolicy>FORCE_DECLARED</projectionPolicy>
  <enabled>true</enabled>
  <metadata>
    <entry key="cachingEnabled">false</entry>
    <entry key="advertised">true</entry>
  </metadata>
  <store class="dataStore">
    <id>DataStoreInfoImpl-2e2377f3:136536dfbc1:-7ffd</id>
  </store>
  <maxFeatures>0</maxFeatures>
  <numDecimals>0</numDecimals>
</featureType>