<dataStore>
  <id>DataStoreInfoImpl-5eae27a8:13e12e44838:-7f73</id>
  <name>ghec_viewer</name>
  <description>ghec_viewer</description>
  <type>PostGIS</type>
  <enabled>true</enabled>
  <workspace>
    <id>WorkspaceInfoImpl-5eae27a8:13e12e44838:-7f75</id>
  </workspace>
  <connectionParameters>
    <entry key="Connection timeout">20</entry>
    <entry key="port">5432</entry>
    <entry key="passwd">AmUXT6TP</entry>
    <entry key="dbtype">postgis</entry>
    <entry key="host">localhost</entry>
    <entry key="validate connections">false</entry>
    <entry key="max connections">10</entry>
    <entry key="database">geonode</entry>
    <entry key="namespace">http://geonode.org/ghec_viewer</entry>
    <entry key="schema">public</entry>
    <entry key="Loose bbox">true</entry>
    <entry key="Expose primary keys">false</entry>
    <entry key="fetch size">1000</entry>
    <entry key="Max open prepared statements">50</entry>
    <entry key="preparedStatements">false</entry>
    <entry key="Estimated extends">true</entry>
    <entry key="user">geonode</entry>
    <entry key="min connections">1</entry>
  </connectionParameters>
  <__default>false</__default>
</dataStore>